webshare/__init__.py
webshare/webshare.py
webshare/util/__init__.py
webshare/util/objects.py
webshareproxy-0.0.10.dist-info/LICENSE
webshareproxy-0.0.10.dist-info/METADATA
webshareproxy-0.0.10.dist-info/WHEEL
webshareproxy-0.0.10.dist-info/top_level.txt
webshareproxy-0.0.10.dist-info/RECORD
