Metadata-Version: 2.1
Name: webshareproxy
Version: 0.0.10
Summary: A Python client library for the Webshare Proxy API, providing easy access to various operations like managing proxies, IP authorizations, user profile, notifications, and more.
Home-page: https://github.com/heromr/webshareproxy
Author: HeroMR
Author-email: mrhero4006@gmail.com
License: MIT
Keywords: python,webshare.io,webshare proxy,free proxy,premium proxy,webshareproxy
Classifier: Development Status :: 5 - Production/Stable
Classifier: Intended Audience :: Developers
Classifier: Programming Language :: Python :: 3
Classifier: Operating System :: OS Independent
License-File: LICENSE
